lxmpay/__init__.py
lxmpay/cache.py
lxmpay/client.py
lxmpay/core.py
lxmpay/errors.py
lxmpay/http.py
lxmpay/lkl_pay.py
lxmpay/models.py
lxmpay/settings.py
lxmpay-0.0.8.dist-info/METADATA
lxmpay-0.0.8.dist-info/WHEEL
lxmpay-0.0.8.dist-info/top_level.txt
lxmpay-0.0.8.dist-info/RECORD
