Metadata-Version: 2.1
Name: lxmpay
Version: 0.0.8
Summary: 旅行梦聚合支付
Home-page: https://github.com
Author: zzz
Author-email: zzz@zzz.com
Project-URL: Source, https://github.com
Keywords: lxmpay
Classifier: Development Status :: 5 - Production/Stable
Classifier: Intended Audience :: Developers
Classifier: Topic :: Software Development :: Build Tools
Classifier: License :: OSI Approved :: MIT License
Classifier: Programming Language :: Python :: 3.9
Classifier: Programming Language :: Python :: Implementation :: CPython
Classifier: Programming Language :: Python :: Implementation :: PyPy
Requires-Dist: pydantic
Requires-Dist: httpx
